pyinteno/__init__.py
pyinteno/py.typed
pyinteno-0.1.2.dist-info/licenses/LICENSE.txt
pyinteno-0.1.2.dist-info/METADATA
pyinteno-0.1.2.dist-info/WHEEL
pyinteno-0.1.2.dist-info/top_level.txt
pyinteno-0.1.2.dist-info/RECORD
