Metadata-Version: 2.4
Name: PyInteno
Version: 0.1.2
Summary: Client for Inteno SolarAPI JSON interface
Author-email: Niels Mündler <n.muendler@web.de>
License: MIT
Project-URL: Repository, https://github.com/nielstron/pyinteno/
Keywords: Inteno,Home Automation,WebSocket,Internet Router
Classifier: Programming Language :: Python :: 3.8
Classifier: Programming Language :: Python :: 3.9
Classifier: Programming Language :: Python :: 3.10
Classifier: Programming Language :: Python :: 3.11
Classifier: Programming Language :: Python :: 3.12
Classifier: Programming Language :: Python :: 3.13
Classifier: Operating System :: OS Independent
Classifier: License :: OSI Approved :: MIT License
Classifier: Development Status :: 3 - Alpha
Classifier: Intended Audience :: Developers
Classifier: Topic :: Software Development :: Object Brokering
Requires-Python: >=3.8.0
License-File: LICENSE.txt
Requires-Dist: websockets
Provides-Extra: dev
Requires-Dist: tox; extra == "dev"
Requires-Dist: ruff; extra == "dev"
Requires-Dist: pytest; extra == "dev"
Dynamic: license-file
